fhir_parse_qs/VERSION
fhir_parse_qs/__init__.py
fhir_parse_qs/update_mappings.py
fhir_parse_qs/mappings/__init__.py
fhir_parse_qs/mappings/account.py
fhir_parse_qs/mappings/activitydefinition.py
fhir_parse_qs/mappings/adverseevent.py
fhir_parse_qs/mappings/allergyintolerance.py
fhir_parse_qs/mappings/appointment.py
fhir_parse_qs/mappings/appointmentresponse.py
fhir_parse_qs/mappings/auditevent.py
fhir_parse_qs/mappings/basic.py
fhir_parse_qs/mappings/bodystructure.py
fhir_parse_qs/mappings/bundle.py
fhir_parse_qs/mappings/capabilitystatement.py
fhir_parse_qs/mappings/careplan.py
fhir_parse_qs/mappings/careteam.py
fhir_parse_qs/mappings/chargeitem.py
fhir_parse_qs/mappings/chargeitemdefinition.py
fhir_parse_qs/mappings/claim.py
fhir_parse_qs/mappings/claimresponse.py
fhir_parse_qs/mappings/clinicalimpression.py
fhir_parse_qs/mappings/codesystem.py
fhir_parse_qs/mappings/common.py
fhir_parse_qs/mappings/communication.py
fhir_parse_qs/mappings/communicationrequest.py
fhir_parse_qs/mappings/compartmentdefinition.py
fhir_parse_qs/mappings/composition.py
fhir_parse_qs/mappings/conceptmap.py
fhir_parse_qs/mappings/condition.py
fhir_parse_qs/mappings/consent.py
fhir_parse_qs/mappings/contract.py
fhir_parse_qs/mappings/control.py
fhir_parse_qs/mappings/coverage.py
fhir_parse_qs/mappings/coverageeligibilityrequest.py
fhir_parse_qs/mappings/coverageeligibilityresponse.py
fhir_parse_qs/mappings/detectedissue.py
fhir_parse_qs/mappings/device.py
fhir_parse_qs/mappings/devicedefinition.py
fhir_parse_qs/mappings/devicemetric.py
fhir_parse_qs/mappings/devicerequest.py
fhir_parse_qs/mappings/deviceusestatement.py
fhir_parse_qs/mappings/diagnosticreport.py
fhir_parse_qs/mappings/documentmanifest.py
fhir_parse_qs/mappings/documentreference.py
fhir_parse_qs/mappings/effectevidencesynthesis.py
fhir_parse_qs/mappings/encounter.py
fhir_parse_qs/mappings/endpoint.py
fhir_parse_qs/mappings/enrollmentrequest.py
fhir_parse_qs/mappings/enrollmentresponse.py
fhir_qs_parser-0.10.0.dist-info/licenses/LICENSE
fhir_qs_parser-0.10.0.dist-info/METADATA
fhir_qs_parser-0.10.0.dist-info/WHEEL
fhir_qs_parser-0.10.0.dist-info/top_level.txt
fhir_qs_parser-0.10.0.dist-info/RECORD
