Metadata-Version: 2.4
Name: fhir-qs-parser
Version: 0.10.0
Summary: Parse FHIR query strings
Home-page: https://github.com/xjodoin/fhir_parse_qs
Author: teffalump
Author-email: teffalump <chris@teffalump.com>
License: GNU General Public License v3 or later (GPLv3+)
Project-URL: Homepage, https://github.com/xjodoin/fhir_parse_qs
Project-URL: Repository, https://github.com/xjodoin/fhir_parse_qs
Classifier: Development Status :: 3 - Alpha
Classifier: Programming Language :: Python
Classifier: Programming Language :: Python :: 3
Classifier: Programming Language :: Python :: 3 :: Only
Classifier: Programming Language :: Python :: 3.8
Classifier: Programming Language :: Python :: 3.9
Classifier: Programming Language :: Python :: 3.10
Classifier: Programming Language :: Python :: 3.11
Classifier: Programming Language :: Python :: 3.12
Classifier: Intended Audience :: Developers
Classifier: License :: OSI Approved :: GNU General Public License v3 or later (GPLv3+)
Classifier: Operating System :: OS Independent
Requires-Python: >=3.8
License-File: LICENSE
Requires-Dist: pendulum>=3
Dynamic: author
Dynamic: home-page
Dynamic: license-file
